LICENSE
MANIFEST.in
README.md
requirements.txt
requirements_dev.txt
setup.cfg
setup.py
tests/__init__.py
tests/test_condition.py
tests/test_webanalyzer.py
webanalyzer/__init__.py
webanalyzer/cli.py
webanalyzer/condition.py
webanalyzer/utils.py
webanalyzer/webanalyzer.py
webanalyzer.egg-info/PKG-INFO
webanalyzer.egg-info/SOURCES.txt
webanalyzer.egg-info/dependency_links.txt
webanalyzer.egg-info/entry_points.txt
webanalyzer.egg-info/not-zip-safe
webanalyzer.egg-info/requires.txt
webanalyzer.egg-info/top_level.txt