Metadata-Version: 2.1
Name: webanalyzer
Version: 2019.8.22
Summary: UNKNOWN
Home-page: https://github.com/webanalyzer/webanalyzer.py
Author: fate0
Author-email: fate0@fatezero.org
License: GPLv2
Keywords: webanalyzer
Platform: UNKNOWN
Classifier: Development Status :: 5 - Production/Stable
Classifier: Intended Audience :: Developers
Classifier: License :: OSI Approved :: Apache Software License
Classifier: Natural Language :: English
Classifier: Programming Language :: Python :: 3.6
Classifier: Programming Language :: Python :: 3.7
